mle_flake8_plugins/__init__.py
mle_flake8_plugins/flake8_mle_convention/__init__.py
mle_flake8_plugins/flake8_mle_convention/disallow_final_w_pydantic.py
mle_flake8_plugins/flake8_mle_convention/errors.py
mle_flake8_plugins/flake8_mle_convention/legacy_type_hint_checker.py
mle_flake8_plugins/flake8_mle_convention/no_operation_checker.py
mle_flake8_plugins/flake8_mle_docstring/__init__.py
mle_flake8_plugins/flake8_mle_docstring/attribute_checker.py
mle_flake8_plugins/flake8_mle_docstring/errors.py
mle_flake8_plugins-0.2.3.dist-info/METADATA
mle_flake8_plugins-0.2.3.dist-info/WHEEL
mle_flake8_plugins-0.2.3.dist-info/entry_points.txt
mle_flake8_plugins-0.2.3.dist-info/RECORD
